pynction/__init__.py
pynction/functors/__init__.py
pynction/functors/function.py
pynction/monads/__init__.py
pynction/monads/either.py
pynction/monads/maybe.py
pynction/monads/try_monad.py
pynction/py.typed
pynction/streams/__init__.py
pynction/streams/stream.py
pynction-0.4.1.dist-info/METADATA
pynction-0.4.1.dist-info/LICENSE
pynction-0.4.1.dist-info/WHEEL
pynction-0.4.1.dist-info/RECORD
