Metadata-Version: 2.1
Name: pynction
Version: 0.4.1
Summary: Functional based library to support monads and other functional programming concepts
Home-page: https://github.com/niconunez96/pynction
License: MIT
Author: Nicolas Nuñez
Author-email: nicolas110996@gmail.com
Maintainer: Nicolas Nuñez
Maintainer-email: nicolas110996@gmail.com
Requires-Python: >=3.7,<4.0
Classifier: Intended Audience :: Developers
Classifier: License :: OSI Approved :: MIT License
Classifier: Operating System :: OS Independent
Classifier: Programming Language :: Python :: 3
Classifier: Programming Language :: Python :: 3.7
Classifier: Programming Language :: Python :: 3.8
Classifier: Programming Language :: Python :: 3.9
Classifier: Programming Language :: Python :: 3.10
Classifier: Programming Language :: Python :: 3.11
Classifier: Programming Language :: Python :: 3
Classifier: Topic :: Software Development
Classifier: Topic :: Utilities
Project-URL: Documentation, https://pynction.vercel.app/
Project-URL: Repository, https://github.com/niconunez96/pynction
